cgse_tools/__init__.py
cgse_tools/cgse_clock.py
cgse_tools/cgse_commands.py
cgse_tools/cgse_services.py
egse/tools/status.py
cgse_tools-2025.0.9.dist-info/METADATA
cgse_tools-2025.0.9.dist-info/WHEEL
cgse_tools-2025.0.9.dist-info/entry_points.txt
cgse_tools-2025.0.9.dist-info/RECORD
